[
	{
		"name": "MZ",
		"type": "target",
		"desc": "",
		"lineNumber": 10
	},
	{
		"name": "",
		"type": "plugindesc",
		"desc": "(v0.5.2) This plugin allows you to type in korean in the Name Input Proccessing <RS_Window_KorNameEdit>",
		"lineNumber": 11
	},
	{
		"name": "biud436",
		"type": "author",
		"desc": "",
		"lineNumber": 12
	},
	{
		"name": "https://biud436.tistory.com/",
		"type": "url",
		"desc": "",
		"lineNumber": 13
	},
	{
		"name": "windowWidth",
		"type": "param",
		"desc": "",
		"lineNumber": 15
	},
	{
		"name": "",
		"type": "desc",
		"desc": "Directly specify the width of a window for editing name.",
		"lineNumber": 16
	},
	{
		"name": "auto",
		"type": "default",
		"desc": "",
		"lineNumber": 18
	},
	{
		"name": "windowCenter",
		"type": "param",
		"desc": "",
		"lineNumber": 20
	},
	{
		"name": "boolean",
		"type": "type",
		"desc": "",
		"lineNumber": 21
	},
	{
		"name": "",
		"type": "desc",
		"desc": "The window will align to the center of the screen unless set the same as 'false' value.",
		"lineNumber": 22
	},
	{
		"name": "false",
		"type": "default",
		"desc": "",
		"lineNumber": 23
	},
	{
		"name": "editWindow_Opacity",
		"type": "param",
		"desc": "",
		"lineNumber": 25
	},
	{
		"name": "number",
		"type": "type",
		"desc": "",
		"lineNumber": 26
	},
	{
		"name": "",
		"type": "desc",
		"desc": "The opacity can set as number between 0 and 255.",
		"lineNumber": 27
	},
	{
		"name": "225",
		"type": "default",
		"desc": "",
		"lineNumber": 28
	},
	{
		"name": "0",
		"type": "min",
		"desc": "",
		"lineNumber": 29
	},
	{
		"name": "255",
		"type": "max",
		"desc": "",
		"lineNumber": 30
	},
	{
		"name": "helpWindow_Opacity",
		"type": "param",
		"desc": "",
		"lineNumber": 32
	},
	{
		"name": "",
		"type": "text",
		"desc": "Help Window Opacity",
		"lineNumber": 33
	},
	{
		"name": "number",
		"type": "type",
		"desc": "",
		"lineNumber": 34
	},
	{
		"name": "",
		"type": "desc",
		"desc": "The opacity can set as number between 0 and 255.",
		"lineNumber": 35
	},
	{
		"name": "225",
		"type": "default",
		"desc": "",
		"lineNumber": 36
	},
	{
		"name": "0",
		"type": "min",
		"desc": "",
		"lineNumber": 37
	},
	{
		"name": "255",
		"type": "max",
		"desc": "",
		"lineNumber": 38
	},
	{
		"name": "askingText",
		"type": "param",
		"desc": "",
		"lineNumber": 40
	},
	{
		"name": "",
		"type": "desc",
		"desc": "This is a text hint",
		"lineNumber": 41
	},
	{
		"name": "",
		"type": "default",
		"desc": "Please enter the name",
		"lineNumber": 42
	},
	{
		"name": "outlineWidth",
		"type": "param",
		"desc": "",
		"lineNumber": 44
	},
	{
		"name": "",
		"type": "desc",
		"desc": "Specify the outline width as you want",
		"lineNumber": 45
	},
	{
		"name": "1",
		"type": "default",
		"desc": "",
		"lineNumber": 46
	},
	{
		"name": "outlineColor",
		"type": "param",
		"desc": "",
		"lineNumber": 48
	},
	{
		"name": "",
		"type": "desc",
		"desc": "Specify the outline color as you want",
		"lineNumber": 49
	},
	{
		"name": "black",
		"type": "default",
		"desc": "",
		"lineNumber": 50
	},
	{
		"name": "fontColor",
		"type": "param",
		"desc": "",
		"lineNumber": 52
	},
	{
		"name": "",
		"type": "desc",
		"desc": "Specify the font color as you want",
		"lineNumber": 53
	},
	{
		"name": "white",
		"type": "default",
		"desc": "",
		"lineNumber": 54
	},
	{
		"name": "standardFontSize",
		"type": "param",
		"desc": "",
		"lineNumber": 56
	},
	{
		"name": "",
		"type": "desc",
		"desc": "Specify the font size as you want",
		"lineNumber": 57
	},
	{
		"name": "28",
		"type": "default",
		"desc": "",
		"lineNumber": 58
	},
	{
		"name": "",
		"type": "param",
		"desc": "Chinese Fonts",
		"lineNumber": 60
	},
	{
		"name": "",
		"type": "desc",
		"desc": "Specify the Chinese font as you want",
		"lineNumber": 61
	},
	{
		"name": "",
		"type": "default",
		"desc": "SimHei, Heiti TC, sans-serif, Noto Sans",
		"lineNumber": 62
	},
	{
		"name": "",
		"type": "param",
		"desc": "Korean Fonts",
		"lineNumber": 64
	},
	{
		"name": "",
		"type": "desc",
		"desc": "Specify the Korean font as you want",
		"lineNumber": 65
	},
	{
		"name": "",
		"type": "default",
		"desc": "Noto Sans, Dotum, AppleGothic, sans-serif",
		"lineNumber": 66
	},
	{
		"name": "",
		"type": "param",
		"desc": "Default Fonts",
		"lineNumber": 68
	},
	{
		"name": "",
		"type": "desc",
		"desc": "Specify the default font as you want",
		"lineNumber": 69
	},
	{
		"name": "GameFont",
		"type": "default",
		"desc": "",
		"lineNumber": 70
	},
	{
		"name": "",
		"type": "param",
		"desc": "Default CharWidth",
		"lineNumber": 72
	},
	{
		"name": "",
		"type": "desc",
		"desc": "This plugin calculates a text width using this letter when the system language is English.",
		"lineNumber": 73
	},
	{
		"name": "A",
		"type": "default",
		"desc": "",
		"lineNumber": 74
	},
	{
		"name": "",
		"type": "param",
		"desc": "Default Background",
		"lineNumber": 76
	},
	{
		"name": "",
		"type": "desc",
		"desc": "Specify the background on your scene for editing the name from img/pictures folder",
		"lineNumber": 77
	},
	{
		"name": "auto",
		"type": "default",
		"desc": "",
		"lineNumber": 79
	},
	{
		"name": "1",
		"type": "require",
		"desc": "",
		"lineNumber": 80
	},
	{
		"name": "img/pictures/",
		"type": "dir",
		"desc": "",
		"lineNumber": 81
	},
	{
		"name": "file",
		"type": "type",
		"desc": "",
		"lineNumber": 82
	},
	{
		"name": "",
		"type": "param",
		"desc": "Default Edit Button",
		"lineNumber": 84
	},
	{
		"name": "",
		"type": "desc",
		"desc": "Specify the button name that would activate the edit window",
		"lineNumber": 85
	},
	{
		"name": "Edit",
		"type": "default",
		"desc": "",
		"lineNumber": 86
	},
	{
		"name": "",
		"type": "param",
		"desc": "Default OK Button",
		"lineNumber": 88
	},
	{
		"name": "",
		"type": "desc",
		"desc": "Specify the button name that would return to previous map after finishing the actor name",
		"lineNumber": 89
	},
	{
		"name": "OK",
		"type": "default",
		"desc": "",
		"lineNumber": 90
	},
	{
		"name": "",
		"type": "param",
		"desc": "Default Cancel Button",
		"lineNumber": 92
	},
	{
		"name": "",
		"type": "desc",
		"desc": "Specify the button name that would return to previous map.",
		"lineNumber": 93
	},
	{
		"name": "Cancel",
		"type": "default",
		"desc": "",
		"lineNumber": 94
	},
	{
		"name": "",
		"type": "param",
		"desc": "Error Message",
		"lineNumber": 96
	},
	{
		"name": "didnt_type_anytext",
		"type": "param",
		"desc": "",
		"lineNumber": 98
	},
	{
		"name": "",
		"type": "parent",
		"desc": "Error Message",
		"lineNumber": 99
	},
	{
		"name": "",
		"type": "desc",
		"desc": "Write here a warning message to be displayed when no letters are entered.",
		"lineNumber": 100
	},
	{
		"name": "",
		"type": "default",
		"desc": "Cannot an empty name",
		"lineNumber": 101
	},
	{
		"name": "cant_type_same_name",
		"type": "param",
		"desc": "",
		"lineNumber": 103
	},
	{
		"name": "",
		"type": "parent",
		"desc": "Error Message",
		"lineNumber": 104
	},
	{
		"name": "",
		"type": "desc",
		"desc": "Write here a warning message to be displayed when texts are the same name.",
		"lineNumber": 105
	},
	{
		"name": "",
		"type": "default",
		"desc": "Cannot set as the same name",
		"lineNumber": 106
	},
	{
		"name": "",
		"type": "param",
		"desc": "Show Error Message",
		"lineNumber": 108
	},
	{
		"name": "",
		"type": "parent",
		"desc": "Error Message",
		"lineNumber": 109
	},
	{
		"name": "boolean",
		"type": "type",
		"desc": "",
		"lineNumber": 110
	},
	{
		"name": "",
		"type": "desc",
		"desc": "Specify whether the error messsage shows.",
		"lineNumber": 111
	},
	{
		"name": "true",
		"type": "default",
		"desc": "",
		"lineNumber": 112
	},
	{
		"name": "true",
		"type": "on",
		"desc": "",
		"lineNumber": 113
	},
	{
		"name": "false",
		"type": "off",
		"desc": "",
		"lineNumber": 114
	},
	{
		"name": "",
		"type": "param",
		"desc": "Keyboard Editor Hidden",
		"lineNumber": 116
	},
	{
		"name": "boolean",
		"type": "type",
		"desc": "",
		"lineNumber": 117
	},
	{
		"name": "",
		"type": "desc",
		"desc": "<input> form allows you to open the virtual keyboard editor on the screen. it can open manually after touching with input form.",
		"lineNumber": 118
	},
	{
		"name": "true",
		"type": "default",
		"desc": "",
		"lineNumber": 119
	},
	{
		"name": "hide",
		"type": "on",
		"desc": "",
		"lineNumber": 120
	},
	{
		"name": "show",
		"type": "off",
		"desc": "",
		"lineNumber": 121
	},
	{
		"name": "Style",
		"type": "param",
		"desc": "",
		"lineNumber": 123
	},
	{
		"name": "struct<TextBox>",
		"type": "type",
		"desc": "",
		"lineNumber": 124
	},
	{
		"name": "",
		"type": "desc",
		"desc": "when showing the input form on the screen, you can change the style of input.",
		"lineNumber": 125
	},
	{
		"name": "",
		"type": "default",
		"desc": "{\"width\":\"60%\",\"textIndent\":\"10px\",\"fontSize\":\"16px\",\"lineHeight\":\"120%\",\"border\":\"3px solid #bd7419\",\"cursor\":\"text\",\"Position\":\"\",\"top\":\"\\\"\\\"\",\"left\":\"\\\"\\\"\",\"right\":\"0\",\"bottom\":\"0\"}",
		"lineNumber": 126
	},
	{
		"name": "",
		"type": "param",
		"desc": "Show Face",
		"lineNumber": 128
	},
	{
		"name": "boolean",
		"type": "type",
		"desc": "",
		"lineNumber": 129
	},
	{
		"name": "",
		"type": "desc",
		"desc": "Specify whther the face image shows.",
		"lineNumber": 130
	},
	{
		"name": "true",
		"type": "default",
		"desc": "",
		"lineNumber": 131
	},
	{
		"name": "true",
		"type": "on",
		"desc": "",
		"lineNumber": 132
	},
	{
		"name": "false",
		"type": "off",
		"desc": "",
		"lineNumber": 133
	},
	{
		"name": "",
		"type": "",
		"desc": "",
		"lineNumber": 135
	},
	{
		"name": "KNE",
		"type": "command",
		"desc": "",
		"lineNumber": 151
	},
	{
		"name": "",
		"type": "text",
		"desc": "Change Plugin Parameters",
		"lineNumber": 152
	},
	{
		"name": "",
		"type": "desc",
		"desc": "This plugin command allows you to change plugin parameters.",
		"lineNumber": 153
	},
	{
		"name": "width",
		"type": "arg",
		"desc": "",
		"lineNumber": 155
	},
	{
		"name": "",
		"type": "desc",
		"desc": "Specify the width of name edit window.",
		"lineNumber": 156
	},
	{
		"name": "580",
		"type": "default",
		"desc": "",
		"lineNumber": 157
	},
	{
		"name": "center",
		"type": "arg",
		"desc": "",
		"lineNumber": 159
	},
	{
		"name": "boolean",
		"type": "type",
		"desc": "",
		"lineNumber": 160
	},
	{
		"name": "",
		"type": "desc",
		"desc": "Sets whether the name window will be placed to center of the screen.",
		"lineNumber": 161
	},
	{
		"name": "true",
		"type": "default",
		"desc": "",
		"lineNumber": 162
	},
	{
		"name": "true",
		"type": "on",
		"desc": "",
		"lineNumber": 163
	},
	{
		"name": "false",
		"type": "off",
		"desc": "",
		"lineNumber": 164
	},
	{
		"name": "outlineWidth",
		"type": "arg",
		"desc": "",
		"lineNumber": 166
	},
	{
		"name": "number",
		"type": "type",
		"desc": "",
		"lineNumber": 167
	},
	{
		"name": "",
		"type": "desc",
		"desc": "Specify the outline width.",
		"lineNumber": 168
	},
	{
		"name": "1",
		"type": "default",
		"desc": "",
		"lineNumber": 169
	},
	{
		"name": "0",
		"type": "min",
		"desc": "",
		"lineNumber": 170
	},
	{
		"name": "outlineColor",
		"type": "arg",
		"desc": "",
		"lineNumber": 172
	},
	{
		"name": "string",
		"type": "type",
		"desc": "",
		"lineNumber": 173
	},
	{
		"name": "",
		"type": "desc",
		"desc": "Specify the outline color as you want.",
		"lineNumber": 174
	},
	{
		"name": "black",
		"type": "default",
		"desc": "",
		"lineNumber": 175
	},
	{
		"name": "textColor",
		"type": "arg",
		"desc": "",
		"lineNumber": 177
	},
	{
		"name": "",
		"type": "text",
		"desc": "Text Color",
		"lineNumber": 178
	},
	{
		"name": "string",
		"type": "type",
		"desc": "",
		"lineNumber": 179
	},
	{
		"name": "",
		"type": "desc",
		"desc": "Specify the desired text color (default : white)",
		"lineNumber": 180
	},
	{
		"name": "white",
		"type": "default",
		"desc": "",
		"lineNumber": 181
	},
	{
		"name": "fontSize",
		"type": "arg",
		"desc": "",
		"lineNumber": 183
	},
	{
		"name": "number",
		"type": "type",
		"desc": "",
		"lineNumber": 184
	},
	{
		"name": "",
		"type": "desc",
		"desc": "Specify the font size (default : 28)",
		"lineNumber": 185
	},
	{
		"name": "28",
		"type": "default",
		"desc": "",
		"lineNumber": 186
	},
	{
		"name": "0",
		"type": "min",
		"desc": "",
		"lineNumber": 187
	},
	{
		"name": "opacity",
		"type": "arg",
		"desc": "",
		"lineNumber": 189
	},
	{
		"name": "number",
		"type": "type",
		"desc": "",
		"lineNumber": 190
	},
	{
		"name": "",
		"type": "desc",
		"desc": "Specify the window opacity (default : 225)",
		"lineNumber": 191
	},
	{
		"name": "225",
		"type": "default",
		"desc": "",
		"lineNumber": 192
	},
	{
		"name": "0",
		"type": "min",
		"desc": "",
		"lineNumber": 193
	},
	{
		"name": "255",
		"type": "max",
		"desc": "",
		"lineNumber": 194
	},
	{
		"name": "askText",
		"type": "arg",
		"desc": "",
		"lineNumber": 196
	},
	{
		"name": "string",
		"type": "type",
		"desc": "",
		"lineNumber": 197
	},
	{
		"name": "",
		"type": "desc",
		"desc": "Specify the default text hint text.",
		"lineNumber": 198
	},
	{
		"name": "",
		"type": "default",
		"desc": "Please enter the name",
		"lineNumber": 199
	},
	{
		"name": "OpenXNameInput",
		"type": "command",
		"desc": "",
		"lineNumber": 201
	},
	{
		"name": "",
		"type": "text",
		"desc": "Open XName Input",
		"lineNumber": 202
	},
	{
		"name": "",
		"type": "desc",
		"desc": "Type the name using IME",
		"lineNumber": 203
	},
	{
		"name": "actorId",
		"type": "arg",
		"desc": "",
		"lineNumber": 205
	},
	{
		"name": "number",
		"type": "type",
		"desc": "",
		"lineNumber": 206
	},
	{
		"name": "",
		"type": "desc",
		"desc": "if -1, actor's id sets as an id of leader.",
		"lineNumber": 207
	},
	{
		"name": "-1",
		"type": "default",
		"desc": "",
		"lineNumber": 208
	},
	{
		"name": "-1",
		"type": "min",
		"desc": "",
		"lineNumber": 209
	},
	{
		"name": "4000",
		"type": "max",
		"desc": "",
		"lineNumber": 210
	},
	{
		"name": "digits",
		"type": "arg",
		"desc": "",
		"lineNumber": 212
	},
	{
		"name": "number",
		"type": "type",
		"desc": "",
		"lineNumber": 213
	},
	{
		"name": "",
		"type": "desc",
		"desc": "Specify the size of the name (default : 6)",
		"lineNumber": 214
	},
	{
		"name": "6",
		"type": "default",
		"desc": "",
		"lineNumber": 215
	},
	{
		"name": "6",
		"type": "min",
		"desc": "",
		"lineNumber": 216
	},
	{
		"name": "width",
		"type": "param",
		"desc": "",
		"lineNumber": 221
	},
	{
		"name": "string",
		"type": "type",
		"desc": "",
		"lineNumber": 222
	},
	{
		"name": "60%",
		"type": "default",
		"desc": "",
		"lineNumber": 223
	},
	{
		"name": "textIndent",
		"type": "param",
		"desc": "",
		"lineNumber": 225
	},
	{
		"name": "string",
		"type": "type",
		"desc": "",
		"lineNumber": 226
	},
	{
		"name": "10px",
		"type": "default",
		"desc": "",
		"lineNumber": 227
	},
	{
		"name": "fontSize",
		"type": "param",
		"desc": "",
		"lineNumber": 229
	},
	{
		"name": "string",
		"type": "type",
		"desc": "",
		"lineNumber": 230
	},
	{
		"name": "16px",
		"type": "default",
		"desc": "",
		"lineNumber": 231
	},
	{
		"name": "lineHeight",
		"type": "param",
		"desc": "",
		"lineNumber": 233
	},
	{
		"name": "string",
		"type": "type",
		"desc": "",
		"lineNumber": 234
	},
	{
		"name": "120%",
		"type": "default",
		"desc": "",
		"lineNumber": 235
	},
	{
		"name": "border",
		"type": "param",
		"desc": "",
		"lineNumber": 237
	},
	{
		"name": "string",
		"type": "type",
		"desc": "",
		"lineNumber": 238
	},
	{
		"name": "",
		"type": "default",
		"desc": "3px solid #bd7419",
		"lineNumber": 239
	},
	{
		"name": "cursor",
		"type": "param",
		"desc": "",
		"lineNumber": 241
	},
	{
		"name": "string",
		"type": "type",
		"desc": "",
		"lineNumber": 242
	},
	{
		"name": "text",
		"type": "default",
		"desc": "",
		"lineNumber": 243
	},
	{
		"name": "Position",
		"type": "param",
		"desc": "",
		"lineNumber": 245
	},
	{
		"name": "top",
		"type": "param",
		"desc": "",
		"lineNumber": 247
	},
	{
		"name": "Position",
		"type": "parent",
		"desc": "",
		"lineNumber": 248
	},
	{
		"name": "\"\"",
		"type": "default",
		"desc": "",
		"lineNumber": 249
	},
	{
		"name": "left",
		"type": "param",
		"desc": "",
		"lineNumber": 251
	},
	{
		"name": "Position",
		"type": "parent",
		"desc": "",
		"lineNumber": 252
	},
	{
		"name": "\"\"",
		"type": "default",
		"desc": "",
		"lineNumber": 253
	},
	{
		"name": "right",
		"type": "param",
		"desc": "",
		"lineNumber": 255
	},
	{
		"name": "Position",
		"type": "parent",
		"desc": "",
		"lineNumber": 256
	},
	{
		"name": "0",
		"type": "default",
		"desc": "",
		"lineNumber": 257
	},
	{
		"name": "bottom",
		"type": "param",
		"desc": "",
		"lineNumber": 259
	},
	{
		"name": "Position",
		"type": "parent",
		"desc": "",
		"lineNumber": 260
	},
	{
		"name": "0",
		"type": "default",
		"desc": "",
		"lineNumber": 261
	},
	{
		"name": "MZ",
		"type": "target",
		"desc": "",
		"lineNumber": 265
	},
	{
		"name": "",
		"type": "plugindesc",
		"desc": "한글 이름 입력 플러그인 <RS_Window_KorNameEdit>",
		"lineNumber": 266
	},
	{
		"name": "러닝은빛(biud436)",
		"type": "author",
		"desc": "",
		"lineNumber": 267
	},
	{
		"name": "https://biud436.blog.me",
		"type": "url",
		"desc": "",
		"lineNumber": 268
	},
	{
		"name": "windowWidth",
		"type": "param",
		"desc": "",
		"lineNumber": 270
	},
	{
		"name": "",
		"type": "text",
		"desc": "창 폭 (가로 크기)",
		"lineNumber": 271
	},
	{
		"name": "",
		"type": "desc",
		"desc": "숫자값을 입력하세요.",
		"lineNumber": 272
	},
	{
		"name": "auto",
		"type": "default",
		"desc": "",
		"lineNumber": 274
	},
	{
		"name": "windowCenter",
		"type": "param",
		"desc": "",
		"lineNumber": 276
	},
	{
		"name": "",
		"type": "text",
		"desc": "화면 중앙 정렬",
		"lineNumber": 277
	},
	{
		"name": "boolean",
		"type": "type",
		"desc": "",
		"lineNumber": 278
	},
	{
		"name": "",
		"type": "desc",
		"desc": "true 또는 false를 입력하세요.",
		"lineNumber": 279
	},
	{
		"name": "false",
		"type": "default",
		"desc": "",
		"lineNumber": 280
	},
	{
		"name": "참",
		"type": "on",
		"desc": "",
		"lineNumber": 281
	},
	{
		"name": "거짓",
		"type": "off",
		"desc": "",
		"lineNumber": 282
	},
	{
		"name": "editWindow_Opacity",
		"type": "param",
		"desc": "",
		"lineNumber": 284
	},
	{
		"name": "투명도",
		"type": "text",
		"desc": "",
		"lineNumber": 285
	},
	{
		"name": "number",
		"type": "type",
		"desc": "",
		"lineNumber": 286
	},
	{
		"name": "",
		"type": "desc",
		"desc": "이름 윈도우의 투명도 값으로 0 ~ 255 사이의 숫자 값을 입력하세요.",
		"lineNumber": 287
	},
	{
		"name": "225",
		"type": "default",
		"desc": "",
		"lineNumber": 288
	},
	{
		"name": "0",
		"type": "min",
		"desc": "",
		"lineNumber": 289
	},
	{
		"name": "255",
		"type": "max",
		"desc": "",
		"lineNumber": 290
	},
	{
		"name": "helpWindow_Opacity",
		"type": "param",
		"desc": "",
		"lineNumber": 292
	},
	{
		"name": "",
		"type": "text",
		"desc": "Help Window 투명도",
		"lineNumber": 293
	},
	{
		"name": "number",
		"type": "type",
		"desc": "",
		"lineNumber": 294
	},
	{
		"name": "",
		"type": "desc",
		"desc": "이름 윈도우의 투명도 값으로 0 ~ 255 사이의 숫자 값을 입력하세요.",
		"lineNumber": 295
	},
	{
		"name": "225",
		"type": "default",
		"desc": "",
		"lineNumber": 296
	},
	{
		"name": "0",
		"type": "min",
		"desc": "",
		"lineNumber": 297
	},
	{
		"name": "255",
		"type": "max",
		"desc": "",
		"lineNumber": 298
	},
	{
		"name": "askingText",
		"type": "param",
		"desc": "",
		"lineNumber": 300
	},
	{
		"name": "",
		"type": "text",
		"desc": "안내 텍스트",
		"lineNumber": 301
	},
	{
		"name": "",
		"type": "desc",
		"desc": "텍스트 힌트",
		"lineNumber": 302
	},
	{
		"name": "",
		"type": "default",
		"desc": "이름을 입력하세요.",
		"lineNumber": 303
	},
	{
		"name": "outlineWidth",
		"type": "param",
		"desc": "",
		"lineNumber": 305
	},
	{
		"name": "",
		"type": "text",
		"desc": "기본 테두리 굵기",
		"lineNumber": 306
	},
	{
		"name": "",
		"type": "desc",
		"desc": "테두리 두께",
		"lineNumber": 307
	},
	{
		"name": "1",
		"type": "default",
		"desc": "",
		"lineNumber": 308
	},
	{
		"name": "outlineColor",
		"type": "param",
		"desc": "",
		"lineNumber": 310
	},
	{
		"name": "",
		"type": "text",
		"desc": "기본 테두리 색상",
		"lineNumber": 311
	},
	{
		"name": "",
		"type": "desc",
		"desc": "테두리 색상",
		"lineNumber": 312
	},
	{
		"name": "black",
		"type": "default",
		"desc": "",
		"lineNumber": 313
	},
	{
		"name": "fontColor",
		"type": "param",
		"desc": "",
		"lineNumber": 315
	},
	{
		"name": "",
		"type": "text",
		"desc": "기본 폰트 색상",
		"lineNumber": 316
	},
	{
		"name": "",
		"type": "desc",
		"desc": "폰트 색상",
		"lineNumber": 317
	},
	{
		"name": "white",
		"type": "default",
		"desc": "",
		"lineNumber": 318
	},
	{
		"name": "standardFontSize",
		"type": "param",
		"desc": "",
		"lineNumber": 320
	},
	{
		"name": "",
		"type": "text",
		"desc": "기본 폰트 크기",
		"lineNumber": 321
	},
	{
		"name": "",
		"type": "desc",
		"desc": "기본 폰트 크기",
		"lineNumber": 322
	},
	{
		"name": "28",
		"type": "default",
		"desc": "",
		"lineNumber": 323
	},
	{
		"name": "",
		"type": "param",
		"desc": "Chinese Fonts",
		"lineNumber": 325
	},
	{
		"name": "",
		"type": "text",
		"desc": "중국어 폰트",
		"lineNumber": 326
	},
	{
		"name": "",
		"type": "desc",
		"desc": "중국어 폰트",
		"lineNumber": 327
	},
	{
		"name": "",
		"type": "default",
		"desc": "SimHei, Heiti TC, sans-serif",
		"lineNumber": 328
	},
	{
		"name": "",
		"type": "param",
		"desc": "Korean Fonts",
		"lineNumber": 330
	},
	{
		"name": "",
		"type": "text",
		"desc": "한글 폰트",
		"lineNumber": 331
	},
	{
		"name": "",
		"type": "desc",
		"desc": "한국어 폰트",
		"lineNumber": 332
	},
	{
		"name": "",
		"type": "default",
		"desc": "나눔고딕, Dotum, AppleGothic, sans-serif",
		"lineNumber": 333
	},
	{
		"name": "",
		"type": "param",
		"desc": "Default Fonts",
		"lineNumber": 335
	},
	{
		"name": "",
		"type": "text",
		"desc": "기본 폰트명",
		"lineNumber": 336
	},
	{
		"name": "",
		"type": "desc",
		"desc": "기본 폰트명은 fonts/gamefont.css에 GameFont로 설정되어있습니다.",
		"lineNumber": 337
	},
	{
		"name": "GameFont",
		"type": "default",
		"desc": "",
		"lineNumber": 338
	},
	{
		"name": "",
		"type": "param",
		"desc": "Default CharWidth",
		"lineNumber": 340
	},
	{
		"name": "",
		"type": "text",
		"desc": "기본 문자 폭 (영어)",
		"lineNumber": 341
	},
	{
		"name": "",
		"type": "desc",
		"desc": "시스템 언어가 영어인 경우, 여기 설정된 텍스트를 사용하여 폭을 계산합니다.",
		"lineNumber": 342
	},
	{
		"name": "A",
		"type": "default",
		"desc": "",
		"lineNumber": 343
	},
	{
		"name": "",
		"type": "param",
		"desc": "Default Background",
		"lineNumber": 345
	},
	{
		"name": "",
		"type": "text",
		"desc": "기본 배경 이미지",
		"lineNumber": 346
	},
	{
		"name": "",
		"type": "desc",
		"desc": "기본 배경으로 쓸 이미지 파일을 설정하세요",
		"lineNumber": 347
	},
	{
		"name": "auto",
		"type": "default",
		"desc": "",
		"lineNumber": 349
	},
	{
		"name": "1",
		"type": "require",
		"desc": "",
		"lineNumber": 350
	},
	{
		"name": "img/pictures/",
		"type": "dir",
		"desc": "",
		"lineNumber": 351
	},
	{
		"name": "file",
		"type": "type",
		"desc": "",
		"lineNumber": 352
	},
	{
		"name": "",
		"type": "param",
		"desc": "Default Edit Button",
		"lineNumber": 354
	},
	{
		"name": "",
		"type": "text",
		"desc": "기본 수정 키 이름",
		"lineNumber": 355
	},
	{
		"name": "",
		"type": "desc",
		"desc": "에디트 윈도우를 활성화 할 수 있는 버튼의 이름입니다",
		"lineNumber": 356
	},
	{
		"name": "수정",
		"type": "default",
		"desc": "",
		"lineNumber": 357
	},
	{
		"name": "",
		"type": "param",
		"desc": "Default OK Button",
		"lineNumber": 359
	},
	{
		"name": "",
		"type": "text",
		"desc": "기본 결정 키 이름",
		"lineNumber": 360
	},
	{
		"name": "",
		"type": "desc",
		"desc": "이름 입력을 끝내고 맵으로 돌아갈 수 있는 버튼의 이름입니다",
		"lineNumber": 361
	},
	{
		"name": "결정",
		"type": "default",
		"desc": "",
		"lineNumber": 362
	},
	{
		"name": "",
		"type": "param",
		"desc": "Default Cancel Button",
		"lineNumber": 364
	},
	{
		"name": "",
		"type": "text",
		"desc": "기본 취소 키 이름",
		"lineNumber": 365
	},
	{
		"name": "",
		"type": "desc",
		"desc": "이름 입력을 취소하고 맵으로 돌아갈 수 있는 버튼의 이름입니다",
		"lineNumber": 366
	},
	{
		"name": "돌아가기",
		"type": "default",
		"desc": "",
		"lineNumber": 367
	},
	{
		"name": "",
		"type": "param",
		"desc": "Error Message",
		"lineNumber": 369
	},
	{
		"name": "",
		"type": "text",
		"desc": "오류 메시지",
		"lineNumber": 370
	},
	{
		"name": "didnt_type_anytext",
		"type": "param",
		"desc": "",
		"lineNumber": 372
	},
	{
		"name": "",
		"type": "text",
		"desc": "이름을 적지 않았을 때",
		"lineNumber": 373
	},
	{
		"name": "",
		"type": "parent",
		"desc": "Error Message",
		"lineNumber": 374
	},
	{
		"name": "",
		"type": "desc",
		"desc": "아무 글자도 입력하지 않았을 때 띄울 메시지를 적으십시오.",
		"lineNumber": 375
	},
	{
		"name": "",
		"type": "default",
		"desc": "아무 글자도 입력하지 않았습니다!",
		"lineNumber": 376
	},
	{
		"name": "cant_type_same_name",
		"type": "param",
		"desc": "",
		"lineNumber": 378
	},
	{
		"name": "",
		"type": "text",
		"desc": "이름이 같을 때",
		"lineNumber": 379
	},
	{
		"name": "",
		"type": "parent",
		"desc": "Error Message",
		"lineNumber": 380
	},
	{
		"name": "",
		"type": "desc",
		"desc": "같은 이름으로 설정하려 할 때 띄울 메시지를 적으십시오.",
		"lineNumber": 381
	},
	{
		"name": "",
		"type": "default",
		"desc": "같은 이름으로 설정할 수 없습니다!",
		"lineNumber": 382
	},
	{
		"name": "",
		"type": "param",
		"desc": "Show Error Message",
		"lineNumber": 384
	},
	{
		"name": "",
		"type": "text",
		"desc": "오류 메시지 표시 여부",
		"lineNumber": 385
	},
	{
		"name": "",
		"type": "parent",
		"desc": "Error Message",
		"lineNumber": 386
	},
	{
		"name": "boolean",
		"type": "type",
		"desc": "",
		"lineNumber": 387
	},
	{
		"name": "",
		"type": "desc",
		"desc": "오류 메시지를 표시할 지 여부를 설정합니다.",
		"lineNumber": 388
	},
	{
		"name": "true",
		"type": "default",
		"desc": "",
		"lineNumber": 389
	},
	{
		"name": "표시한다",
		"type": "on",
		"desc": "",
		"lineNumber": 390
	},
	{
		"name": "표시안함",
		"type": "off",
		"desc": "",
		"lineNumber": 391
	},
	{
		"name": "",
		"type": "param",
		"desc": "Keyboard Editor Hidden",
		"lineNumber": 393
	},
	{
		"name": "boolean",
		"type": "type",
		"desc": "",
		"lineNumber": 394
	},
	{
		"name": "",
		"type": "desc",
		"desc": "모바일에서 입력 양식을 터치하여 수동으로 가상 키보드 입력기를 띄울 수 있게 하는 기능입니다.",
		"lineNumber": 395
	},
	{
		"name": "true",
		"type": "default",
		"desc": "",
		"lineNumber": 396
	},
	{
		"name": "숨김",
		"type": "on",
		"desc": "",
		"lineNumber": 397
	},
	{
		"name": "보임",
		"type": "off",
		"desc": "",
		"lineNumber": 398
	},
	{
		"name": "Style",
		"type": "param",
		"desc": "",
		"lineNumber": 400
	},
	{
		"name": "struct<TextBox>",
		"type": "type",
		"desc": "",
		"lineNumber": 401
	},
	{
		"name": "",
		"type": "desc",
		"desc": "입력 양식의 스타일을 설정할 수 있습니다 (기본적으로는 하단에 표시됨)",
		"lineNumber": 402
	},
	{
		"name": "",
		"type": "default",
		"desc": "{\"width\":\"60%\",\"textIndent\":\"10px\",\"fontSize\":\"16px\",\"lineHeight\":\"120%\",\"border\":\"3px solid #bd7419\",\"cursor\":\"text\",\"Position\":\"\",\"top\":\"\\\"\\\"\",\"left\":\"\\\"\\\"\",\"right\":\"0\",\"bottom\":\"0\"}",
		"lineNumber": 403
	},
	{
		"name": "",
		"type": "param",
		"desc": "Show Face",
		"lineNumber": 405
	},
	{
		"name": "",
		"type": "text",
		"desc": "얼굴 이미지 표시",
		"lineNumber": 406
	},
	{
		"name": "boolean",
		"type": "type",
		"desc": "",
		"lineNumber": 407
	},
	{
		"name": "",
		"type": "desc",
		"desc": "얼굴 이미지 표시 여부를 설정합니다.",
		"lineNumber": 408
	},
	{
		"name": "true",
		"type": "default",
		"desc": "",
		"lineNumber": 409
	},
	{
		"name": "표시",
		"type": "on",
		"desc": "",
		"lineNumber": 410
	},
	{
		"name": "감추기",
		"type": "off",
		"desc": "",
		"lineNumber": 411
	},
	{
		"name": "",
		"type": "",
		"desc": "",
		"lineNumber": 413
	},
	{
		"name": "KNE",
		"type": "command",
		"desc": "",
		"lineNumber": 424
	},
	{
		"name": "",
		"type": "text",
		"desc": "플러그인 매개변수 변경",
		"lineNumber": 425
	},
	{
		"name": "",
		"type": "desc",
		"desc": "플러그인 매개변수를 변경할 수 있습니다.",
		"lineNumber": 426
	},
	{
		"name": "width",
		"type": "arg",
		"desc": "",
		"lineNumber": 428
	},
	{
		"name": "폭",
		"type": "text",
		"desc": "",
		"lineNumber": 429
	},
	{
		"name": "",
		"type": "desc",
		"desc": "이름 편집 윈도우의 폭을 지정하세요 (기본값 : 580)",
		"lineNumber": 430
	},
	{
		"name": "580",
		"type": "default",
		"desc": "",
		"lineNumber": 431
	},
	{
		"name": "center",
		"type": "arg",
		"desc": "",
		"lineNumber": 433
	},
	{
		"name": "",
		"type": "text",
		"desc": "중앙 정렬",
		"lineNumber": 434
	},
	{
		"name": "boolean",
		"type": "type",
		"desc": "",
		"lineNumber": 435
	},
	{
		"name": "",
		"type": "desc",
		"desc": "창을 정확히 중앙에 정렬하고자 한다면 참으로 설정하세요",
		"lineNumber": 436
	},
	{
		"name": "true",
		"type": "default",
		"desc": "",
		"lineNumber": 437
	},
	{
		"name": "참",
		"type": "on",
		"desc": "",
		"lineNumber": 438
	},
	{
		"name": "거짓",
		"type": "off",
		"desc": "",
		"lineNumber": 439
	},
	{
		"name": "outlineWidth",
		"type": "arg",
		"desc": "",
		"lineNumber": 441
	},
	{
		"name": "",
		"type": "text",
		"desc": "테두리 굵기",
		"lineNumber": 442
	},
	{
		"name": "number",
		"type": "type",
		"desc": "",
		"lineNumber": 443
	},
	{
		"name": "",
		"type": "desc",
		"desc": "폰트의 테두리 굵기를 설정하세요 (기본값 : 1)",
		"lineNumber": 444
	},
	{
		"name": "1",
		"type": "default",
		"desc": "",
		"lineNumber": 445
	},
	{
		"name": "0",
		"type": "min",
		"desc": "",
		"lineNumber": 446
	},
	{
		"name": "outlineColor",
		"type": "arg",
		"desc": "",
		"lineNumber": 448
	},
	{
		"name": "",
		"type": "text",
		"desc": "테두리 색상",
		"lineNumber": 449
	},
	{
		"name": "string",
		"type": "type",
		"desc": "",
		"lineNumber": 450
	},
	{
		"name": "",
		"type": "desc",
		"desc": "원하는 테두리 색상을 지정하세요 (기본값 : black)",
		"lineNumber": 451
	},
	{
		"name": "black",
		"type": "default",
		"desc": "",
		"lineNumber": 452
	},
	{
		"name": "textColor",
		"type": "arg",
		"desc": "",
		"lineNumber": 454
	},
	{
		"name": "",
		"type": "text",
		"desc": "텍스트 색상",
		"lineNumber": 455
	},
	{
		"name": "",
		"type": "text",
		"desc": "Text Color",
		"lineNumber": 456
	},
	{
		"name": "string",
		"type": "type",
		"desc": "",
		"lineNumber": 457
	},
	{
		"name": "",
		"type": "desc",
		"desc": "텍스트 색상을 변경할 수 있습니다 (기본값 : white)",
		"lineNumber": 458
	},
	{
		"name": "white",
		"type": "default",
		"desc": "",
		"lineNumber": 459
	},
	{
		"name": "fontSize",
		"type": "arg",
		"desc": "",
		"lineNumber": 461
	},
	{
		"name": "",
		"type": "text",
		"desc": "폰트 크기",
		"lineNumber": 462
	},
	{
		"name": "number",
		"type": "type",
		"desc": "",
		"lineNumber": 463
	},
	{
		"name": "",
		"type": "desc",
		"desc": "폰트의 크기를 설정하세요 (기본값 : 28)",
		"lineNumber": 464
	},
	{
		"name": "28",
		"type": "default",
		"desc": "",
		"lineNumber": 465
	},
	{
		"name": "0",
		"type": "min",
		"desc": "",
		"lineNumber": 466
	},
	{
		"name": "opacity",
		"type": "arg",
		"desc": "",
		"lineNumber": 468
	},
	{
		"name": "투명도",
		"type": "text",
		"desc": "",
		"lineNumber": 469
	},
	{
		"name": "number",
		"type": "type",
		"desc": "",
		"lineNumber": 470
	},
	{
		"name": "",
		"type": "desc",
		"desc": "투명도를 설정하세요 (기본값 : 225)",
		"lineNumber": 471
	},
	{
		"name": "225",
		"type": "default",
		"desc": "",
		"lineNumber": 472
	},
	{
		"name": "0",
		"type": "min",
		"desc": "",
		"lineNumber": 473
	},
	{
		"name": "255",
		"type": "max",
		"desc": "",
		"lineNumber": 474
	},
	{
		"name": "askText",
		"type": "arg",
		"desc": "",
		"lineNumber": 476
	},
	{
		"name": "",
		"type": "text",
		"desc": "안내 텍스트",
		"lineNumber": 477
	},
	{
		"name": "string",
		"type": "type",
		"desc": "",
		"lineNumber": 478
	},
	{
		"name": "",
		"type": "desc",
		"desc": "안내 텍스트를 설정하세요",
		"lineNumber": 479
	},
	{
		"name": "",
		"type": "default",
		"desc": "Please enter the name",
		"lineNumber": 480
	},
	{
		"name": "OpenXNameInput",
		"type": "command",
		"desc": "",
		"lineNumber": 482
	},
	{
		"name": "",
		"type": "text",
		"desc": "이름 8자 이상 입력 받기",
		"lineNumber": 483
	},
	{
		"name": "",
		"type": "desc",
		"desc": "8자 이상의 이름을 설정하고자 할 때 사용하는 플러그인 명령입니다.",
		"lineNumber": 484
	},
	{
		"name": "actorId",
		"type": "arg",
		"desc": "",
		"lineNumber": 486
	},
	{
		"name": "number",
		"type": "type",
		"desc": "",
		"lineNumber": 487
	},
	{
		"name": "",
		"type": "desc",
		"desc": "-1로 설정하면 자동으로 리더 파티원으로 설정됩니다.",
		"lineNumber": 488
	},
	{
		"name": "-1",
		"type": "default",
		"desc": "",
		"lineNumber": 489
	},
	{
		"name": "-1",
		"type": "min",
		"desc": "",
		"lineNumber": 490
	},
	{
		"name": "4000",
		"type": "max",
		"desc": "",
		"lineNumber": 491
	},
	{
		"name": "digits",
		"type": "arg",
		"desc": "",
		"lineNumber": 493
	},
	{
		"name": "number",
		"type": "type",
		"desc": "",
		"lineNumber": 494
	},
	{
		"name": "",
		"type": "desc",
		"desc": "이름의 길이를 입력하세요 (기본값 : 6)",
		"lineNumber": 495
	},
	{
		"name": "6",
		"type": "default",
		"desc": "",
		"lineNumber": 496
	},
	{
		"name": "6",
		"type": "min",
		"desc": "",
		"lineNumber": 497
	},
	{
		"name": "width",
		"type": "param",
		"desc": "",
		"lineNumber": 502
	},
	{
		"name": "string",
		"type": "type",
		"desc": "",
		"lineNumber": 503
	},
	{
		"name": "60%",
		"type": "default",
		"desc": "",
		"lineNumber": 504
	},
	{
		"name": "textIndent",
		"type": "param",
		"desc": "",
		"lineNumber": 506
	},
	{
		"name": "string",
		"type": "type",
		"desc": "",
		"lineNumber": 507
	},
	{
		"name": "10px",
		"type": "default",
		"desc": "",
		"lineNumber": 508
	},
	{
		"name": "fontSize",
		"type": "param",
		"desc": "",
		"lineNumber": 510
	},
	{
		"name": "string",
		"type": "type",
		"desc": "",
		"lineNumber": 511
	},
	{
		"name": "16px",
		"type": "default",
		"desc": "",
		"lineNumber": 512
	},
	{
		"name": "lineHeight",
		"type": "param",
		"desc": "",
		"lineNumber": 514
	},
	{
		"name": "string",
		"type": "type",
		"desc": "",
		"lineNumber": 515
	},
	{
		"name": "120%",
		"type": "default",
		"desc": "",
		"lineNumber": 516
	},
	{
		"name": "border",
		"type": "param",
		"desc": "",
		"lineNumber": 518
	},
	{
		"name": "string",
		"type": "type",
		"desc": "",
		"lineNumber": 519
	},
	{
		"name": "",
		"type": "default",
		"desc": "3px solid #bd7419",
		"lineNumber": 520
	},
	{
		"name": "cursor",
		"type": "param",
		"desc": "",
		"lineNumber": 522
	},
	{
		"name": "string",
		"type": "type",
		"desc": "",
		"lineNumber": 523
	},
	{
		"name": "text",
		"type": "default",
		"desc": "",
		"lineNumber": 524
	},
	{
		"name": "Position",
		"type": "param",
		"desc": "",
		"lineNumber": 526
	},
	{
		"name": "top",
		"type": "param",
		"desc": "",
		"lineNumber": 528
	},
	{
		"name": "Position",
		"type": "parent",
		"desc": "",
		"lineNumber": 529
	},
	{
		"name": "\"\"",
		"type": "default",
		"desc": "",
		"lineNumber": 530
	},
	{
		"name": "left",
		"type": "param",
		"desc": "",
		"lineNumber": 532
	},
	{
		"name": "Position",
		"type": "parent",
		"desc": "",
		"lineNumber": 533
	},
	{
		"name": "\"\"",
		"type": "default",
		"desc": "",
		"lineNumber": 534
	},
	{
		"name": "right",
		"type": "param",
		"desc": "",
		"lineNumber": 536
	},
	{
		"name": "Position",
		"type": "parent",
		"desc": "",
		"lineNumber": 537
	},
	{
		"name": "0",
		"type": "default",
		"desc": "",
		"lineNumber": 538
	},
	{
		"name": "bottom",
		"type": "param",
		"desc": "",
		"lineNumber": 540
	},
	{
		"name": "Position",
		"type": "parent",
		"desc": "",
		"lineNumber": 541
	},
	{
		"name": "0",
		"type": "default",
		"desc": "",
		"lineNumber": 542
	},
	{
		"name": "",
		"type": "",
		"desc": "",
		"lineNumber": 654
	},
	{
		"name": "TextBox",
		"type": "class",
		"desc": "",
		"lineNumber": 675
	},
	{
		"name": "commandInput",
		"type": "method",
		"desc": "",
		"lineNumber": 1266
	},
	{
		"name": "commandCancel",
		"type": "method",
		"desc": "",
		"lineNumber": 1277
	}
]